ascend_boto3/__init__.py
ascend_boto3/control.py
ascend_boto3/risk_classifier.py
ascend_boto3/wrapper.py
ascend_boto3_wrapper-1.0.0.dist-info/licenses/LICENSE
ascend_boto3_wrapper-1.0.0.dist-info/METADATA
ascend_boto3_wrapper-1.0.0.dist-info/WHEEL
ascend_boto3_wrapper-1.0.0.dist-info/top_level.txt
ascend_boto3_wrapper-1.0.0.dist-info/RECORD
