Metadata-Version: 2.4
Name: ascend-boto3-wrapper
Version: 1.0.0
Summary: ASCEND AI Governance wrapper for boto3 - Automatic governance for AWS SDK operations
Author-email: OW-kai Corporation <support@ascendowkai.com>
License: Proprietary
Project-URL: Homepage, https://docs.ascendowkai.com
Project-URL: Documentation, https://docs.ascendowkai.com/sdk/boto3
Project-URL: Repository, https://github.com/owkai/ascend-boto3-wrapper
Project-URL: Changelog, https://github.com/owkai/ascend-boto3-wrapper/blob/main/CHANGELOG.md
Keywords: ascend,governance,ai-governance,boto3,aws,sdk,enterprise,security,compliance
Classifier: Development Status :: 4 - Beta
Classifier: Intended Audience :: Developers
Classifier: License :: Other/Proprietary License
Classifier: Operating System :: OS Independent
Classifier: Programming Language :: Python :: 3
Classifier: Programming Language :: Python :: 3.9
Classifier: Programming Language :: Python :: 3.10
Classifier: Programming Language :: Python :: 3.11
Classifier: Programming Language :: Python :: 3.12
Classifier: Topic :: Security
Classifier: Topic :: Software Development :: Libraries :: Python Modules
Requires-Python: >=3.9
License-File: LICENSE
Requires-Dist: boto3>=1.28.0
Requires-Dist: ascend-ai-sdk>=1.0.0
Provides-Extra: dev
Requires-Dist: pytest>=8.0.0; extra == "dev"
Requires-Dist: pytest-cov>=4.0.0; extra == "dev"
Requires-Dist: pytest-asyncio>=0.23.0; extra == "dev"
Requires-Dist: moto>=5.0.0; extra == "dev"
Dynamic: license-file
